pylf/__init__.py
pylf/_core.py
pylf/_exceptions.py
pylf/_misc.py
pylf/_numeric_ordered_set.py
pylf/_page.py
pylf/_template.py
pylf-4.1.0.dist-info/LICENSE.txt
pylf-4.1.0.dist-info/METADATA
pylf-4.1.0.dist-info/WHEEL
pylf-4.1.0.dist-info/top_level.txt
pylf-4.1.0.dist-info/zip-safe
pylf-4.1.0.dist-info/RECORD
