Metadata-Version: 2.1
Name: pylf
Version: 4.1.0
Summary: A lightweight Python library for simulating Chinese handwriting
Home-page: https://github.com/Gsllchb/PyLf
Author: Gsllchb
Author-email: Gsllchb@gmail.com
License: bsd-3-clause
Keywords: simulating Chinese handwriting
Platform: UNKNOWN
Classifier: Programming Language :: Python :: 3.5
Classifier: Programming Language :: Python :: 3.6
Classifier: Programming Language :: Python :: 3.7
Classifier: Programming Language :: Python :: Implementation :: CPython
Requires-Python: >= 3.5
Requires-Dist: pillow (<7,>=5)
